django_smart_cache/__init__.py
django_smart_cache/apps.py
django_smart_cache/cache.py
django_smart_cache/models.py
django_smart_cache/py.typed
django_smart_cache/views.py
django_smart_cache/viewsets.py
django_smart_cache-0.1.2.dist-info/METADATA
django_smart_cache-0.1.2.dist-info/WHEEL
django_smart_cache-0.1.2.dist-info/RECORD
