Metadata-Version: 2.4
Name: django-smart-cache
Version: 0.1.2
Summary: Biblioteca de cache incrivelmente poderosa para Django.
Project-URL: Homepage, https://github.com/Alan-Gomes1/django-smart-cache
Project-URL: Issues, https://github.com/Alan-Gomes1/django-smart-cache/issues
Author-email: Alan Gomes <alan.gomes.ag28@gmail.com>
Classifier: Development Status :: 3 - Alpha
Classifier: Environment :: Web Environment
Classifier: Framework :: Django
Classifier: Framework :: Django :: 2.2
Classifier: Framework :: Django :: 4.2
Classifier: Framework :: Django :: 5.0
Classifier: Intended Audience :: Developers
Classifier: License :: OSI Approved :: MIT License
Classifier: Operating System :: OS Independent
Classifier: Programming Language :: Python
Classifier: Programming Language :: Python :: 3
Classifier: Programming Language :: Python :: 3.8
Classifier: Topic :: Software Development :: Libraries :: Python Modules
Requires-Python: >=3.8
Requires-Dist: django>=2.2
Requires-Dist: djangorestframework>=3.10
Provides-Extra: dev
Requires-Dist: pytest-django>=4.11.1; extra == 'dev'
Requires-Dist: pytest>=8.3.1; extra == 'dev'
